CHANGES.rst
LICENSE
MANIFEST.in
README.rst
package.json
setup.py
armstrong/__init__.py
armstrong.core.arm_layout.egg-info/PKG-INFO
armstrong.core.arm_layout.egg-info/SOURCES.txt
armstrong.core.arm_layout.egg-info/dependency_links.txt
armstrong.core.arm_layout.egg-info/namespace_packages.txt
armstrong.core.arm_layout.egg-info/requires.txt
armstrong.core.arm_layout.egg-info/top_level.txt
armstrong/core/__init__.py
armstrong/core/arm_layout/__init__.py
armstrong/core/arm_layout/mixins.py
armstrong/core/arm_layout/models.py
armstrong/core/arm_layout/utils.py
armstrong/core/arm_layout/backends/__init__.py
armstrong/core/arm_layout/backends/basic.py
armstrong/core/arm_layout/backends/model_provided.py
armstrong/core/arm_layout/templatetags/__init__.py
armstrong/core/arm_layout/templatetags/layout_helpers.py