Metadata-Version: 1.1
Name: armstrong.core.arm-layout
Version: 1.4.0
Summary: Layout code related to Armstrong
Home-page: http://github.com/armstrong/armstrong.core.arm_layout/
Author: Texas Tribune & The Center for Investigative Reporting
Author-email: dev@armstrongcms.org
License: UNKNOWN
Platform: UNKNOWN
Classifier: Development Status :: 5 - Production/Stable
Classifier: Environment :: Web Environment
Classifier: Framework :: Django
Classifier: Intended Audience :: Developers
Classifier: License :: OSI Approved :: Apache Software License
Classifier: Operating System :: OS Independent
Classifier: Programming Language :: Python
Classifier: Programming Language :: Python :: 2.6
Classifier: Programming Language :: Python :: 2.7
